poxy/__init__.py
poxy/cppreference-doxygen-web.tag.xml
poxy/css.py
poxy/doxygen.py
poxy/emoji.py
poxy/fixers.py
poxy/graph.py
poxy/main.py
poxy/mcss.py
poxy/paths.py
poxy/project.py
poxy/repos.py
poxy/run.py
poxy/schemas.py
poxy/soup.py
poxy/svg.py
poxy/utils.py
poxy/version.py
poxy/version.txt
poxy/xml_utils.py
poxy/css/m-special.css
poxy/css/m-theme-dark.css
poxy/css/m-theme-light.css
poxy/css/poxy-overrides.css
poxy/css/poxy-pygments.css
poxy/css/poxy-theme-dark.css
poxy/css/poxy-theme-light.css
poxy/css/poxy.css
poxy/generated/6aa12ac32e258617e37a0030dc54f789b894368b.css
poxy/generated/emoji.json
poxy/generated/poxy.css
poxy/generated/fonts/6xK1dSBYKcSV-LCoeQqfX1RYOo3qPZ7jsDJT9g.woff2
poxy/generated/fonts/6xK1dSBYKcSV-LCoeQqfX1RYOo3qPZ7ksDJT9g.woff2
poxy/generated/fonts/6xK1dSBYKcSV-LCoeQqfX1RYOo3qPZ7nsDI.woff2
poxy/generated/fonts/6xK1dSBYKcSV-LCoeQqfX1RYOo3qPZ7osDJT9g.woff2
poxy/generated/fonts/6xK1dSBYKcSV-LCoeQqfX1RYOo3qPZ7psDJT9g.woff2
poxy/generated/fonts/6xK1dSBYKcSV-LCoeQqfX1RYOo3qPZ7qsDJT9g.woff2
poxy/generated/fonts/6xK1dSBYKcSV-LCoeQqfX1RYOo3qPZ7rsDJT9g.woff2
poxy/generated/fonts/6xK3dSBYKcSV-LCoeQqfX1RYOo3qN67lqDY.woff2
poxy/generated/fonts/6xK3dSBYKcSV-LCoeQqfX1RYOo3qNK7lqDY.woff2
poxy/generated/fonts/6xK3dSBYKcSV-LCoeQqfX1RYOo3qNa7lqDY.woff2
poxy/generated/fonts/6xK3dSBYKcSV-LCoeQqfX1RYOo3qNq7lqDY.woff2
poxy/generated/fonts/6xK3dSBYKcSV-LCoeQqfX1RYOo3qO67lqDY.woff2
poxy/generated/fonts/6xK3dSBYKcSV-LCoeQqfX1RYOo3qOK7l.woff2
poxy/generated/fonts/6xK3dSBYKcSV-LCoeQqfX1RYOo3qPK7lqDY.woff2
poxy/generated/fonts/6xKwdSBYKcSV-LCoeQqfX1RYOo3qPZY4lCdg18Smxg.woff2
poxy/generated/fonts/6xKwdSBYKcSV-LCoeQqfX1RYOo3qPZY4lCdh18Smxg.woff2
poxy/generated/fonts/6xKwdSBYKcSV-LCoeQqfX1RYOo3qPZY4lCdi18Smxg.woff2
poxy/generated/fonts/6xKwdSBYKcSV-LCoeQqfX1RYOo3qPZY4lCdj18Smxg.woff2
poxy/generated/fonts/6xKwdSBYKcSV-LCoeQqfX1RYOo3qPZY4lCdo18Smxg.woff2
poxy/generated/fonts/6xKwdSBYKcSV-LCoeQqfX1RYOo3qPZY4lCds18Q.woff2
poxy-0.20.0.dist-info/licenses/LICENSE.txt
poxy-0.20.0.dist-info/METADATA
poxy-0.20.0.dist-info/WHEEL
poxy-0.20.0.dist-info/entry_points.txt
poxy-0.20.0.dist-info/top_level.txt
poxy-0.20.0.dist-info/zip-safe
poxy-0.20.0.dist-info/RECORD
