Metadata-Version: 2.4
Name: poxy
Version: 0.20.0
Summary: Documentation generator for C++.
Author-email: Mark Gillard <mark.gillard@outlook.com.au>
License: MIT
Project-URL: Source, https://github.com/marzer/poxy
Project-URL: Tracker, https://github.com/marzer/poxy/issues
Project-URL: Funding, https://github.com/sponsors/marzer
Keywords: c++,doxygen,documentation
Classifier: Development Status :: 4 - Beta
Classifier: License :: OSI Approved :: MIT License
Classifier: Programming Language :: C++
Classifier: Topic :: Documentation
Classifier: Topic :: Software Development :: Code Generators
Classifier: Topic :: Software Development :: Documentation
Classifier: Topic :: Utilities
Requires-Python: >=3.7
License-File: LICENSE.txt
Requires-Dist: misk>=0.8.1
Requires-Dist: bs4
Requires-Dist: jinja2
Requires-Dist: pygments
Requires-Dist: html5lib
Requires-Dist: lxml
Requires-Dist: tomli
Requires-Dist: schema!=0.7.5
Requires-Dist: requests
Requires-Dist: trieregex
Requires-Dist: colorama
Dynamic: license-file
